dl_on_flink_tensorflow-0.5.0.dist-info/top_level.txt
dl_on_flink_tensorflow-0.5.0.dist-info/WHEEL
dl_on_flink_tensorflow-0.5.0.dist-info/METADATA
dl_on_flink_tensorflow-0.5.0.dist-info/RECORD
dl_on_flink_tensorflow/libflink_ops.so
dl_on_flink_tensorflow/tf_utils.py
dl_on_flink_tensorflow/table_sinks.py
dl_on_flink_tensorflow/tensorflow_TFConfig.py
dl_on_flink_tensorflow/tensorflow_on_flink_ops.py
dl_on_flink_tensorflow/tfrecord_table_source.py
dl_on_flink_tensorflow/tensorflow_on_flink_mlconf.py
dl_on_flink_tensorflow/tensorflow_on_flink_tfconf.py
dl_on_flink_tensorflow/tensorflow_context.py
dl_on_flink_tensorflow/tensorflow_on_flink_table.py
dl_on_flink_tensorflow/tfrecord_source_func.py
dl_on_flink_tensorflow/flink_row_writer.py
dl_on_flink_tensorflow/version.py
dl_on_flink_tensorflow/tf_cluster_config.py
dl_on_flink_tensorflow/__init__.py
dl_on_flink_tensorflow/gpu_info.py
dl_on_flink_tensorflow/flink_ml/tf_estimator.py
dl_on_flink_tensorflow/flink_ml/tf_multi_worker_entry.py
dl_on_flink_tensorflow/flink_ml/tf_model_factory.py
dl_on_flink_tensorflow/flink_ml/tf_estimator_constants.py
dl_on_flink_tensorflow/flink_ml/__init__.py
