Metadata-Version: 2.1
Name: dl-on-flink-tensorflow
Version: 0.5.0
Home-page: https://github.com/flink-extended/dl-on-flink
License: https://www.apache.org/licenses/LICENSE-2.0
Requires-Python: >=3.6,<3.8
Requires-Dist: tensorflow (<2.0.0,>=1.15.0)
Requires-Dist: tensorboard (<2.0.0,>=1.15.0)
Requires-Dist: dl-on-flink-framework (==0.5.0)
Requires-Dist: apache-flink (<1.15.0,>=1.14.0)
Requires-Dist: apache-flink-ml (<3.0.0,>=2.0.0)
Requires-Dist: cloudpickle (>=1.2.2)
Requires-Dist: protobuf (<3.18)
Requires-Dist: grpcio (<1.47.0,>=1.24.3)
